LICENSE
README.md
setup.py
CVE_2022_0165.egg-info/PKG-INFO
CVE_2022_0165.egg-info/SOURCES.txt
CVE_2022_0165.egg-info/dependency_links.txt
CVE_2022_0165.egg-info/entry_points.txt
CVE_2022_0165.egg-info/requires.txt
CVE_2022_0165.egg-info/top_level.txt
cve20220165/__init__.py
cve20220165/main.py
cve20220165/includes/__init__.py
cve20220165/includes/bot.py
cve20220165/includes/filereader.py
cve20220165/includes/scan.py
cve20220165/includes/writefile.py
cve20220165/utils/__init__.py
cve20220165/utils/configure.py
cve20220165/utils/const.py
cve20220165/utils/helpers.py
cve20220165/utils/status.py